django_ulid/__init__.py
django_ulid/forms.py
django_ulid/models.py
django_ulid/serializers.py
django_ulid-0.0.4.dist-info/LICENSE
django_ulid-0.0.4.dist-info/METADATA
django_ulid-0.0.4.dist-info/WHEEL
django_ulid-0.0.4.dist-info/top_level.txt
django_ulid-0.0.4.dist-info/RECORD
